Metadata-Version: 2.1
Name: color-dtu-design
Version: 0.0
Summary: DTU colors
Home-page: UNKNOWN
Author-email: cathrinehan29@hotmail.com
License: UNKNOWN
Platform: UNKNOWN
